README.rst
setup.py
netcdf4_pydap/__init__.py
netcdf4_pydap/core.py
netcdf4_pydap/httpserver.py
netcdf4_pydap/sessions.py
netcdf4_pydap.egg-info/PKG-INFO
netcdf4_pydap.egg-info/SOURCES.txt
netcdf4_pydap.egg-info/dependency_links.txt
netcdf4_pydap.egg-info/not-zip-safe
netcdf4_pydap.egg-info/requires.txt
netcdf4_pydap.egg-info/top_level.txt
netcdf4_pydap/cas/__init__.py
netcdf4_pydap/cas/esgf.py
netcdf4_pydap/cas/get_cookies.py
netcdf4_pydap/requests_pydap/__init__.py
netcdf4_pydap/requests_pydap/http.py
netcdf4_pydap/requests_pydap/proxy.py