Metadata-Version: 1.1
Name: netcdf4-pydap
Version: 0.2.6
Summary: netCDF4 and CAS compatibility layer for pydap
Home-page: UNKNOWN
Author: F. B. Laliberte
Author-email: laliberte.frederic@gmail.com
License: MIT
Keywords: atmosphere climate
Platform: UNKNOWN
Classifier: Development Status :: 4 - Beta
Classifier: Intended Audience :: Science/Research
Classifier: Natural Language :: English
Classifier: License :: OSI Approved :: BSD License
Classifier: Programming Language :: Python :: 2.7
Classifier: Programming Language :: Fortran
